XinGainianMoniDianlu3YunsuanFangdaqiDePinlvtexingHeLvboqiFix1/README.md
XinGainianMoniDianlu3YunsuanFangdaqiDePinlvtexingHeLvboqiFix1/__init__.py
XinGainianMoniDianlu3YunsuanFangdaqiDePinlvtexingHeLvboqiFix1/__main__.py
XinGainianMoniDianlu3YunsuanFangdaqiDePinlvtexingHeLvboqiFix1/file.pdf
XinGainianMoniDianlu3YunsuanFangdaqiDePinlvtexingHeLvboqiFix1/index.html
xin_gainian_moni_dianlu_3_yunsuan_fangdaqi_de_pinlvtexing_he_lvboqi_fix1-2025.3.24.0.dist-info/METADATA
xin_gainian_moni_dianlu_3_yunsuan_fangdaqi_de_pinlvtexing_he_lvboqi_fix1-2025.3.24.0.dist-info/WHEEL
xin_gainian_moni_dianlu_3_yunsuan_fangdaqi_de_pinlvtexing_he_lvboqi_fix1-2025.3.24.0.dist-info/entry_points.txt
xin_gainian_moni_dianlu_3_yunsuan_fangdaqi_de_pinlvtexing_he_lvboqi_fix1-2025.3.24.0.dist-info/top_level.txt
xin_gainian_moni_dianlu_3_yunsuan_fangdaqi_de_pinlvtexing_he_lvboqi_fix1-2025.3.24.0.dist-info/RECORD
